{"ВТ 22":[{"title":"Презантація освітньо-розважальної програми Національного музею Тараса Шевченко  «Peace &Love by Shevchenko»","date":"22 вересня","time":"","place":"Дитячий простір (11 Павільйон)","tag":"Дитяча програма","url":"/ukr/programm/1575"},{"title":"За цією стороною екрану","date":"22 вересня","time":"","place":"Візуальна програма (21 павільйон)","tag":"Візуальне мистецтво","url":"/ukr/programm/1636"},{"title":"MOLODIYA Майстер-клас ","date":"22 вересня","time":"12:00","place":"Кінотеатр (6 Павільйон)","tag":"Кіно","url":"/ukr/programm/1010"},{"title":"МК від СТБ: Максим Листвинов","date":"22 вересня","time":"12:00","place":"Лекторій (2 Павільйон)","tag":"Освітня програма","url":"/ukr/programm/1687"},{"title":"Презентація проектів від #Babylon’13","date":"22 вересня","time":"13:30","place":"Кінотеатр (6 Павільйон)","tag":"Кіно","url":"/ukr/programm/1019"},{"title":"Випускники","date":"22 вересня","time":"14:00","place":"DIYA (Кіностудія імені Довженка)","tag":"Кіно","url":"/ukr/programm/1527"},{"title":"\"Незалежність\". Кінопоказ та лекторій в рамках Фестивалю Американського кіно","date":"22 вересня","time":"14:00","place":"DIYA (Кіностудія імені Довженка)","tag":"Освітня програма","url":"/ukr/programm/1728"},{"title":"\"По колу\" та \"Къырым\"","date":"22 вересня","time":"15:00","place":"Кінотеатр (6 Павільйон)","tag":"Кіно","url":"/ukr/programm/1027"},{"title":"Майстер-клас школи сучасної хореографії \"Тотем\" ","date":"22 вересня","time":"15:00","place":"Дитячий простір (11 Павільйон)","tag":"Дитяча програма","url":"/ukr/programm/1355"},{"title":"Як хактивізм та технотворчість можуть дати відповідь на енергетичні виклики.","date":"22 вересня","time":"15:00","place":"Еко-простір \"Берізки\"","tag":"Еко-програма","url":"/ukr/programm/1473"},{"title":"Майстер-клас пластилінової анімації ","date":"22 вересня","time":"15:00","place":"Дитячий простір (11 Павільйон)","tag":"Дитяча програма","url":"/ukr/programm/1541"},{"title":"Хатха-йога.","date":"22 вересня","time":"15:00 - 16:00","place":"Еко-простір \"Берізки\"","tag":"Еко-програма","url":"/ukr/programm/1754"},{"title":"Спецпроект. Творча програма для особливих діток. Спецкіно, спецхореографія, спецтеатр.","date":"22 вересня","time":"15:00-17:00","place":"Дитячий простір (11 Павільйон)","tag":"Дитяча програма","url":"/ukr/programm/1539"},{"title":"Показ програми міжнародного фестивалю відеоарта \"InMediTerraneum (IMT)\" ","date":"22 вересня","time":"15:00-18:00, 20:00-23:00","place":"Візуальна програма (21 павільйон)","tag":"Візуальне мистецтво","url":"/ukr/programm/1637"},{"title":"GogolfotoLab: Основи фотографії. Портрет. Коммунікація з моделлю. Схеми світла. Практикум","date":"22 вересня","time":"15:30","place":"Візуальна програма (21 павільйон)","tag":"Візуальне мистецтво","url":"/ukr/programm/1620"},{"title":"Відкриті публічні майстер-класи фахівців Music Arts Academy для всіх бажаючих.","date":"22 вересня","time":"16:00","place":"Дитячий простір (11 Павільйон)","tag":"Дитяча програма","url":"/ukr/programm/1359"},{"title":"Від мрій до дій. Створюємо арт-простір на берегах Либеді.","date":"22 вересня","time":"16:00 ","place":"Еко-простір \"Берізки\"","tag":"Еко-програма","url":"/ukr/programm/1474"},{"title":"Надзвичайно гучно і неймовірно близько ","date":"22 вересня","time":"16:00","place":"Хореографія (13 Павільйон)","tag":"Танець","url":"/ukr/programm/1512"},{"title":"GogolfotoLab: Пінхол. Історія та сучасні світові тенденції. Виготовлення найпростішого паперового фотоапарата. Фотопленер. Частина 2","date":"22 вересня","time":"16:00","place":"Візуальна програма (21 павільйон)","tag":"Візуальне мистецтво","url":"/ukr/programm/1625"},{"title":"Workshop для не-дизайнерів. Створення унікальних меблів.","date":"22 вересня","time":"16:00 - 19:00","place":"39 Павільйон","tag":"Еко-програма","url":"/ukr/programm/1032"},{"title":"DOCUDAYS UA: показ-презентація The Guardian Pitch в Україні","date":"22 вересня","time":"16:30 - 18:00","place":"Кінотеатр (6 Павільйон)","tag":"Кіно","url":"/ukr/programm/1034"},{"title":"презентація театру Biuro Podrozy (Познань)","date":"22 вересня","time":"17:00","place":"Велика Сцена-1 (9 Павільйон)","tag":"Театр","url":"/ukr/programm/1035"},{"title":"Казки на ніч","date":"22 вересня","time":"17:00","place":"Дитячий простір (11 Павільйон)","tag":"Дитяча програма","url":"/ukr/programm/1362"},{"title":"Нова Парадигма: території інтелектуальної свободи","date":"22 вересня","time":"17:00","place":"Лекторій (2 Павільйон)","tag":"Освітня програма","url":"/ukr/programm/1686"},{"title":"[Арт-МК] Магія миловаріння МК","date":"22 вересня","time":"17:00","place":"DIYA (Кіностудія імені Довженка)","tag":"Освітня програма","url":"/ukr/programm/1727"},{"title":"Від атомної електростанції до арт-об'єкту.","date":"22 вересня","time":"17:30 - 19:00","place":"Еко-простір \"Берізки\"","tag":"Еко-програма","url":"/ukr/programm/1480"},{"title":"Українське #лядство","date":"22 вересня","time":"18:00","place":"Театральна мала сцена (17 Павільйон)","tag":"Театр","url":"/ukr/programm/1047"},{"title":"Театральна мафія. Кожному можна приміряти на себе будь-який образ і відіграти найбільш непередбачуваний сценарій.","date":"22 вересня","time":"18:00","place":"Дитячий простір (11 Павільйон)","tag":"Дитяча програма","url":"/ukr/programm/1365"},{"title":"Дискусія « Що варто робити під час виховання дитини аби уникнути проблем нарко- та алко- залежності в майбутньому»","date":"22 вересня","time":"18:00","place":"Дитячий простір (11 Павільйон)","tag":"Дитяча програма","url":"/ukr/programm/1548"},{"title":"GogolfotoLab: Технологія кольорового ручного друку з аналогових носіїв. Фотолабораторний практикум. Частина 1.","date":"22 вересня","time":"18:00","place":"Візуальна програма (21 павільйон)","tag":"Візуальне мистецтво","url":"/ukr/programm/1638"},{"title":"[science] цикл МК з робототехніки та 3-D моделюванню та друку","date":"22 вересня","time":"18:00","place":"DIYA (Кіностудія імені Довженка)","tag":"Освітня програма","url":"/ukr/programm/1726"},{"title":"Фестиваль \"Кіно без бар'єрів\": \"Король каліка\", \"Пошкоджений мозком\"","date":"22 вересня","time":"18:00 - 19:30 ","place":"Кінотеатр (6 Павільйон)","tag":"Кіно","url":"/ukr/programm/1043"},{"title":"Сольний концерт Христини Соловій. Презентація альбому. Електронний концерт гуцульської культури від Gutzul Magic Foundation ","date":"22 вересня","time":"18:30","place":"Альтернативна музична сцена (19 Павільйон)","tag":"Альтернативна Музика","url":"/ukr/programm/1427"},{"title":"Антігона","date":"22 вересня","time":"19:00","place":"DIYA (Кіностудія імені Довженка)","tag":"Театр","url":"/ukr/programm/1050"},{"title":"[ре]архівація: Швейки чеської літератури: Гашек, Шкворецький, Грабал","date":"22 вересня","time":"19:00","place":"Літературний простір (38 Павільйон)","tag":"Література","url":"/ukr/programm/1056"},{"title":"Підпілля","date":"22 вересня","time":"19:00","place":"Дім освіти та культури «Майстер Клас»","tag":"Театр","url":"/ukr/programm/1517"},{"title":"Показ анімації від студії \"Новаторфільм\". Серії \"Моя країна- Україна\"","date":"22 вересня","time":"19:00","place":"Дитячий простір (11 Павільйон)","tag":"Дитяча програма","url":"/ukr/programm/1540"},{"title":"[3C] Сократичні бесіди на тему \"Cоціум у інформаційну епоху\"","date":"22 вересня","time":"19:00","place":"Лекторій (2 Павільйон)","tag":"Освітня програма","url":"/ukr/programm/1685"},{"title":"[MusicStart] Написання  композиції та запис","date":"22 вересня","time":"19:00","place":"DIYA (Кіностудія імені Довженка)","tag":"Освітня програма","url":"/ukr/programm/1724"},{"title":"[Арт-МК] Відкрита майстерня кераміки","date":"22 вересня","time":"19:00","place":"DIYA (Кіностудія імені Довженка)","tag":"Освітня програма","url":"/ukr/programm/1725"},{"title":"\"Київ-Москва\" 2 частина","date":"22 вересня","time":"19:30","place":"Кінотеатр (6 Павільйон)","tag":"Кіно","url":"/ukr/programm/1061"},{"title":"Еко-батл. Настільні ігри. Чайна.","date":"22 вересня","time":"19:30 - 21:00","place":"Еко-простір \"Берізки\"","tag":"Еко-програма","url":"/ukr/programm/1066"},{"title":"R+J","date":"22 вересня","time":"20:00","place":"Театральна велика сцена (17 Павільйон)","tag":"Театр","url":"/ukr/programm/1067"},{"title":"Розмова: Іван Рябчій та Роман Кабачій про роман Мішеля Уельбека \"Покора\"","date":"22 вересня","time":"20:00","place":"Літературний простір (38 Павільйон)","tag":"Література","url":"/ukr/programm/1073"},{"title":"Арт-проект \"Зайві Люди\" ","date":"22 вересня","time":"20:00","place":"D.O.T підземна сцена (42 павільйон)","tag":"Альтернативна Музика","url":"/ukr/programm/1519"},{"title":"Театр просто неба: вистава «Лисий Лев».","date":"22 вересня","time":"20:00 - 20:30","place":"Еко-простір \"Берізки\"","tag":"Еко-програма","url":"/ukr/programm/1057"},{"title":"Коридор","date":"22 вересня","time":"20:00-21:00","place":"Хореографія (13 Павільйон)","tag":"Танець","url":"/ukr/programm/1076"},{"title":"У затишку білих акацій","date":"22 вересня","time":"21:00","place":"Кінотеатр (6 Павільйон)","tag":"Кіно","url":"/ukr/programm/1086"},{"title":"Джем-сейшн.","date":"22 вересня","time":"21:00","place":"Еко-простір \"Берізки\"","tag":"Еко-програма","url":"/ukr/programm/1095"}]}
